src/alu.sv
/*
ALU module, which takes two operands of size 32-bits each and a 4-bit ALU_control as input.
Operation is performed on the basis of ALU_control value and output is 32-bit ALU_result. 
If the ALU_result is zero, a ZERO FLAG is set.
*/

/*
ALU Control lines | Function
-----------------------------
        0000    Bitwise-AND
        0001    Bitwise-OR
        0010	Add (A+B)
        0100	Subtract (A-B)
        1000	Set on less than
        0011    Shift left logical
        0101    Shift right logical
        0110    Multiply
        0111    Bitwise-XOR
        1001    Not
        1011    mov
        1010    div
        1101    mod
*/

module alu(
    input [31:0] A,B, 
    input[3:0] alu_control,
    output reg [31:0] alu_result,
    output reg zero_flag 
);
    always @(*)
    begin
        // Operating based on control input
        case(alu_control)

        4'b0000: alu_result = A&B;
        4'b0001: alu_result = A|B;
        4'b0010: alu_result = A+B;
        4'b0110: alu_result = A-B;
        4'b0011: begin 
            if(A<B)
            alu_result = 1;
            else
            alu_result = 0;
        end
        4'b0100: alu_result = A<<B;
        4'b0111: alu_result = A>>B;
        4'b0101: alu_result = A*B;  //multiply
        4'b0111: alu_result = A^B; //xor
        4'b1000: alu_result = ~A;  //not
        4'b1001: alu_result = B;  //mov
        4'b1010: alu_result = A/B; //div
        4'b1101: alu_result = A%B; //mod

        endcase

        // Setting Zero_flag if ALU_result is zero
        if (alu_result == 0)
            zero_flag = 1'b1;
        else
            zero_flag = 1'b0;
        
    end
endmodule

src/alu_tb.sv
`include "alu.sv"

module alu_tb ();
    reg [31:0] A,B;
    reg [3:0] ALUControl;
    wire ZERO;
    wire [31:0] ALUResult;

    // Instantiating modules
    alu ALU_module(.A(A),.B(B),.alu_control(ALUControl),.zero_flag(ZERO),.alu_result(ALUResult));

    // Setting up waveform
    initial
    begin
        $dumpfile("output_wave.vcd");
        $dumpvars(0,alu_tb);
    end 

    // Monitoring changing values
    initial
    $monitor($time, "\nInput_1 = %b, \nInput_2 = %b,\nALU_control = %b,\n ALU_result = %b, Zero_flag = %b\n",A,B,ALUControl,ALUResult,ZERO);

    // Test conditions
    initial
    begin
        A = 23; B = 42;  ALUControl = 4'b0000;
    #20 A = 23; B = 42;  ALUControl = 4'b0001;
    #20 A = 23; B = 42;  ALUControl = 4'b0010;
    #20 A = 23; B = 42;  ALUControl = 4'b0100;
    #20 A = 23; B = 42;  ALUControl = 4'b1000;
    #20 A = 42; B = 23;  ALUControl = 4'b1000;
    #20 A = 42; B = 23;  ALUControl = 4'b0100;
    #20 A = 42; B = 23;  ALUControl = 4'b1001;
    #20 A = 42; B = 23;  ALUControl = 4'b1011;
    #20 A = 42; B = 23;  ALUControl = 4'b1010;
    #20 A = 42; B = 23;  ALUControl = 4'b1101;
    
    end

    // Finish after 250 clock cycles
    initial
    #250 $finish;

endmodule

project_1/project_1.sim/sim_1/behav/xsim/output_wave.vcd
$date
   Tue Jan 31 10:25:43 2023
$end
$version
  2018.2
$end
$timescale
  1ps
$end
$scope module alu_tb $end
$var reg 32 ! A [31:0] $end
$var reg 32 " B [31:0] $end
$var reg 4 # ALUControl [3:0] $end
$var wire 1 $ ZERO $end
$var wire 32 % ALUResult [31:0] $end
$scope module ALU_module $end
$var wire 32 & A [31:0] $end
$var wire 32 ' B [31:0] $end
$var wire 4 ( alu_control [3:0] $end
$var reg 32 ) alu_result [31:0] $end
$var reg 1 * zero_flag $end
$upscope $end
$upscope $end
$enddefinitions $end
#0
$dumpvars
b10111 !
b101010 "
b0 #
0$
bx %
b10111 &
b101010 '
b0 (
bx )
0*
$end
#20000
b10111 !
b101010 "
b1 #
b10 %
b1 (
b10 )
0*
#40000
b10111 !
b101010 "
b10 #
b111111 %
b10 (
b111111 )
0*
#60000
b10111 !
b101010 "
b100 #
b11111111111111111111111111101101 %
b100 (
b11111111111111111111111111101101 )
0*
#80000
b10111 !
b101010 "
b1000 #
b1111000110 %
b1000 (
b1111000110 )
0*
#100000
b101010 !
b10111 "
b1000 #
b101010 &
b10111 '
b1111000110 )
0*
#120000
b101010 !
b10111 "
b100 #
b10011 %
b100 (
b10011 )
0*
#140000
b101010 !
b10111 "
b1001 #
b111101 %
b1001 (
b111101 )
0*
#160000
b101010 !
b10111 "
b1011 #
b10111 %
b1011 (
b10111 )
0*
#180000
b101010 !
b10111 "
b1010 #
b11111111111111111111111111010101 %
b1010 (
b11111111111111111111111111010101 )
0*
#200000
b101010 !
b10111 "
b1101 #
b10011 %
b1101 (
b10011 )
0*
